{
    "skoda":"SKODA",
    "toyota":"TOYOTA",
    "services":"Services",
    "name":"English Name",
    "arabic_name":"Arabic Name",
    "description":"Description",
    "arabic_description":"Arabic Description",
    "upload_photo":"Upload Photo",
    "image_thumbnail":"Image thumbnail",
    "submit_now":"Submit Now",
    "cancel":"cancel",
    "main_service":"Main service in page",
    "service_information" : "Service Information",
    "add_edit_service" : "Add / edit Service",
    "select_lang":"Select Language",
    "english":"English",
    "arabic":"Arabic",
    "my_account":"My Account",
    "sign_out":"Sign Out",
    "models":"Models",
    "service_center":"Service Center",
    "spare_parts":"Spare Parts",
    "cars":"Cars",
    "buy":"Buy Car",
    "sell":"Sell Car",
    "exchange":"Exchange Car",
    "contact_us":"Contact Us",
    "home":"Home",
    "requested_services":"Requested Services",
    "request_services":"Request Services",
    "service_without_description":"Service without description",
    "service_with_description":"Service with description",
    "service_in_slider":"Full range of services",
    "schedule_service":"Schedule for Service",
    "phone": "Phone",
    "email": "Email",
    "car_brand": "Car Brand",
    "car_model": "Car Model",
    "chassis_no": "Chassis No",
    "service_hours":"Service Hours:",
    "add_image_slider":"Add Image to Slider",
    "image_info":"Image Information",
    "add_image_body":"Add Image to body",
    "brochures":"Brochures",
    "file_info":"File Information",
    "upload_file":"Upload  File",
    "add_edit_car":"ADD / EDIT CAR",
    "vehicle_info":"Vehicle Information",
    "specs":"Specifications",
    "body":"Body",
    "transmission":"Transmission",
    "fuel_type":"Fuel Type",
    "engine":"Engine",
    "reg_year":"Reg Year",
    "fuel_economy":"Fuel Economy",
    "add_edit_spare_part":"Add / edit Spare Part",
    "spare_part_info":"Spare Part Information",
    "price":"Price"

}